trestle_fedramp/__init__.py
trestle_fedramp/const.py
trestle_fedramp/commands/__init__.py
trestle_fedramp/commands/transform.py
trestle_fedramp/commands/validate.py
trestle_fedramp/core/__init__.py
trestle_fedramp/core/baselines.py
trestle_fedramp/core/docx_helper.py
trestle_fedramp/core/fedramp.py
trestle_fedramp/core/fedramp_values.py
trestle_fedramp/core/format_convert.py
trestle_fedramp/core/ssp_reader.py
trestle_fedramp/resources/__init__.py
trestle_fedramp/resources/fedramp-source/ssp.xsl
trestle_fedramp/resources/fedramp-source/content/baselines/rev5/xml/FedRAMP_rev5_HIGH-baseline-resolved-profile_catalog.xml
trestle_fedramp/resources/fedramp-source/content/baselines/rev5/xml/FedRAMP_rev5_HIGH-baseline_profile.xml
trestle_fedramp/resources/fedramp-source/content/baselines/rev5/xml/FedRAMP_rev5_LI-SaaS-baseline-resolved-profile_catalog.xml
trestle_fedramp/resources/fedramp-source/content/baselines/rev5/xml/FedRAMP_rev5_LI-SaaS-baseline_profile.xml
trestle_fedramp/resources/fedramp-source/content/baselines/rev5/xml/FedRAMP_rev5_LOW-baseline-resolved-profile_catalog.xml
trestle_fedramp/resources/fedramp-source/content/baselines/rev5/xml/FedRAMP_rev5_LOW-baseline_profile.xml
trestle_fedramp/resources/fedramp-source/content/baselines/rev5/xml/FedRAMP_rev5_MODERATE-baseline-resolved-profile_catalog.xml
trestle_fedramp/resources/fedramp-source/content/baselines/rev5/xml/FedRAMP_rev5_MODERATE-baseline_profile.xml
trestle_fedramp/resources/fedramp-source/content/resources/xml/FedRAMP_extensions.xml
trestle_fedramp/resources/fedramp-source/content/resources/xml/fedramp_threats.xml
trestle_fedramp/resources/fedramp-source/content/resources/xml/fedramp_values.xml
trestle_fedramp/resources/fedramp-source/content/resources/xml/information-types.xml
trestle_fedramp/resources/fedramp-source/content/templates/SSP-Appendix-A-High-FedRAMP-Security-Controls.docx
trestle_fedramp/resources/fedramp-source/content/templates/SSP-Appendix-A-Low-FedRAMP-Security-Controls.docx
compliance_trestle_fedramp-0.4.0.dist-info/LICENSE
compliance_trestle_fedramp-0.4.0.dist-info/METADATA
compliance_trestle_fedramp-0.4.0.dist-info/WHEEL
compliance_trestle_fedramp-0.4.0.dist-info/top_level.txt
compliance_trestle_fedramp-0.4.0.dist-info/RECORD
