Metadata-Version: 2.1
Name: compliance-trestle-fedramp
Version: 0.4.0
Summary: Trestle plugin for FedRAMP validation and format conversion
Home-page: https://github.com/oscal-compass/compliance-trestle-fedramp
Author: IBM
Author-email: avikas@in.ibm.com
License: Apache Software License v2
Classifier: Development Status :: 4 - Beta
Classifier: Environment :: Console
Classifier: Intended Audience :: Developers
Classifier: Intended Audience :: Information Technology
Classifier: License :: OSI Approved :: Apache Software License
Classifier: Operating System :: POSIX
Classifier: Operating System :: Microsoft
Classifier: Programming Language :: Python :: 3
Classifier: Programming Language :: Python :: 3.9
Classifier: Programming Language :: Python :: 3.10
Classifier: Programming Language :: Python :: 3.11
License-File: LICENSE
Requires-Dist: compliance-trestle>=3.3.0
Requires-Dist: saxonche>=12.4.1.0
Requires-Dist: python-docx>=1.1.0
Provides-Extra: dev
Requires-Dist: pytest>=5.4.3; extra == "dev"
Requires-Dist: pytest-cov>=2.10.0; extra == "dev"
Requires-Dist: pytest-xdist; extra == "dev"
Requires-Dist: pre-commit>=2.4.0; extra == "dev"
Requires-Dist: setuptools; extra == "dev"
Requires-Dist: wheel; extra == "dev"
Requires-Dist: yapf; extra == "dev"
Requires-Dist: python-semantic-release>=9.8.0; extra == "dev"
Requires-Dist: pep8-naming; extra == "dev"
Requires-Dist: pytest-random-order; extra == "dev"
Requires-Dist: python-dateutil; extra == "dev"
Requires-Dist: mypy; extra == "dev"
Requires-Dist: mkdocs; extra == "dev"
Requires-Dist: mkdocstrings; extra == "dev"
Requires-Dist: mkdocs-material; extra == "dev"
Requires-Dist: markdown-include; extra == "dev"
Requires-Dist: pymdown-extensions; extra == "dev"
Requires-Dist: livereload; extra == "dev"
Requires-Dist: pylint; extra == "dev"
